.gitignore
CHANGES.rst
MANIFEST.in
README.rst
README.txt
setup.py
kss/__init__.py
kss.plugin.timer.egg-info/PKG-INFO
kss.plugin.timer.egg-info/SOURCES.txt
kss.plugin.timer.egg-info/dependency_links.txt
kss.plugin.timer.egg-info/entry_points.txt
kss.plugin.timer.egg-info/namespace_packages.txt
kss.plugin.timer.egg-info/requires.txt
kss.plugin.timer.egg-info/top_level.txt
kss/plugin/__init__.py
kss/plugin/timer/__init__.py
kss/plugin/timer/commands.py
kss/plugin/timer/config.py
kss/plugin/timer/configure.zcml
kss/plugin/timer/kss.plugin.timer-configure.zcml
kss/plugin/timer/demo/__init__.py
kss/plugin/timer/demo/configure.zcml
kss/plugin/timer/demo/kss_timer_demo.css
kss/plugin/timer/demo/kss_timer_demo.kss
kss/plugin/timer/demo/kss_timer_demo.pt
kss/plugin/timer/demo/zopeconfig.py
kss/plugin/timer/javascript/kss_timer.js
kss/plugin/timer/tests/__init__.py
kss/plugin/timer/tests/jstestcase.py
kss/plugin/timer/tests/test_timer.js
kss/plugin/timer/tests/test_timer.py