Metadata-Version: 1.0
Name: kss.plugin.timer
Version: 1.1
Summary: Timer plugin for KSS
Home-page: https://plone.org/products/extreme-management-tool/
Author: Guido Wesdorp and Zest software
Author-email: info@zestsoftware.nl
License: UNKNOWN
Platform: UNKNOWN
